r_config/__init__.py
r_config/r_config.py
r_config-0.4.2.dist-info/METADATA
r_config-0.4.2.dist-info/WHEEL
r_config-0.4.2.dist-info/top_level.txt
r_config-0.4.2.dist-info/RECORD
