Metadata-Version: 2.1
Name: r_config
Version: 0.4.2
Summary: A customized way to use config
Home-page: https://github.com/LiterallyTheOne/r_config
Author: Ramin Zarebidoky
Author-email: ramin.zarebidoky@gmail.com
Requires-Python: >3.9.0
Requires-Dist: pyyaml
